{
  "tasks": [
    {
      "id": 1771940996122,
      "name": "地理跨学科",
      "completed": false,
      "countdown": {
        "totalSeconds": 3360,
        "remainingSeconds": 3360,
        "startTime": null,
        "isRunning": false
      },
      "start": "2026-02-24",
      "time": 56,
      "deadline": "2026-02-25",
      "tags": [
        "地理"
      ]
    },
    {
      "name": "生物跨学科",
      "start": "2026-02-24",
      "time": 56,
      "deadline": "2026-02-25",
      "completed": false,
      "actualTime": null,
      "aiSuggestedTime": null,
      "id": 1771938402547,
      "countdown": {
        "totalSeconds": 3360,
        "remainingSeconds": 3360,
        "startTime": null,
        "isRunning": false
      },
      "tags": [
        "生物"
      ]
    },
    {
      "name": "道法",
      "start": "2026-02-24",
      "time": 50,
      "deadline": "2026-02-24",
      "completed": false,
      "actualTime": null,
      "aiSuggestedTime": null,
      "id": 1771938383730,
      "countdown": {
        "totalSeconds": 3000,
        "remainingSeconds": 3000,
        "startTime": null,
        "isRunning": false
      },
      "tags": [
        "道法"
      ]
    },
    {
      "name": "历史",
      "start": "2026-02-24",
      "time": 31,
      "deadline": "2026-02-24",
      "completed": false,
      "actualTime": null,
      "aiSuggestedTime": null,
      "id": 1771938361329,
      "countdown": {
        "totalSeconds": 1860,
        "remainingSeconds": 1860,
        "startTime": null,
        "isRunning": false
      },
      "tags": [
        "历史"
      ]
    },
    {
      "name": "化学第4讲ABC 第5讲C",
      "start": "2026-02-24",
      "time": 55,
      "deadline": "2026-02-26",
      "completed": false,
      "actualTime": null,
      "aiSuggestedTime": null,
      "id": 1771938224859,
      "countdown": {
        "totalSeconds": 3300,
        "remainingSeconds": 3300,
        "startTime": null,
        "isRunning": false
      },
      "tags": [
        "化学"
      ]
    }
  ],
  "time": "2026-02-24T16:59:55.323Z"
}